edit_operation-1.0.0.dist-info/RECORD
edit_operation-1.0.0.dist-info/METADATA
edit_operation-1.0.0.dist-info/top_level.txt
edit_operation-1.0.0.dist-info/WHEEL
edit_operation/levenshtein.cpython-37m-x86_64-linux-gnu.so
