Metadata-Version: 2.1
Name: edit-operation
Version: 1.0.0
Summary: "Get the edit operations of two string"
Home-page: https://github.com/xcTorres/edit_operation
Author: xcTorres
Author-email: xcwhu2016@gmail.com
License: UNKNOWN
Project-URL: Bug Tracker, https://github.com/xcTorres/edit_operation/issues
Platform: UNKNOWN
Classifier: Programming Language :: Python :: 3
Classifier: License :: OSI Approved :: MIT License
Classifier: Operating System :: OS Independent
Requires-Python: >=3.6
